Metadata-Version: 2.1
Name: LDB-Inventory-Barcode
Version: 0.14.1
Summary: Create standard barcodes with Python. No external modules needed. (optional Pillow support included).
Home-page: https://www.eldebe.org/ldb/inventory/barcode/
Author: Alex Orange
Author-email: alex@eldebe.org
License: LICENSE
Platform: UNKNOWN
Classifier: Development Status :: 5 - Production/Stable
Classifier: Environment :: Console
Classifier: Intended Audience :: Developers
Classifier: License :: OSI Approved :: GNU Affero General Public License v3
Classifier: Operating System :: OS Independent
Classifier: Programming Language :: Python
Classifier: Programming Language :: Python :: 3
Classifier: Programming Language :: Python :: 3.6
Classifier: Programming Language :: Python :: 3.7
Classifier: Programming Language :: Python :: 3.8
Classifier: Programming Language :: Python :: 3.9
Classifier: Topic :: Multimedia :: Graphics
Classifier: Topic :: Software Development :: Libraries :: Python Modules
Provides-Extra: images
Provides-Extra: pdf
